dummyfilescreator/__init__.py
dummyfilescreator/__main__.py
dummyfilescreator/dfc_cli.py
dummyfilescreator/dfc_ui.py
dummyfilescreator/files_creator.py
dummyfilescreator/logger.py
dummyfilescreator/qt_about_window.py
dummyfilescreator/qt_icon.py
dummyfilescreator/qt_main_window.py
dummyfilescreator-3.0.1.dist-info/LICENSE
dummyfilescreator-3.0.1.dist-info/METADATA
dummyfilescreator-3.0.1.dist-info/WHEEL
dummyfilescreator-3.0.1.dist-info/entry_points.txt
dummyfilescreator-3.0.1.dist-info/top_level.txt
dummyfilescreator-3.0.1.dist-info/RECORD
