Metadata-Version: 2.1
Name: dummyfilescreator
Version: 3.0.1
Summary: Desktop & CLI tool to generate dummy files
Home-page: https://github.com/matuzalemmuller/dummy-files-creator
Author: Matuzalem (Mat) Muller
Author-email: matuzalemtech@gmail.com
License: GPLv3
Classifier: Development Status :: 5 - Production/Stable
Classifier: Intended Audience :: Information Technology
Classifier: Operating System :: OS Independent
Classifier: License :: OSI Approved :: GNU General Public License v3 (GPLv3)
Classifier: Topic :: Software Development :: Quality Assurance
Requires-Python: >=3.6
License-File: LICENSE
Requires-Dist: PyQt5 (>=5.15.0)
Requires-Dist: tqdm (>=4.64.0)
